LICENSE.txt
README.md
setup.py
Topsis_SAVITAJ_102016034/__init__.py
Topsis_SAVITAJ_102016034/topsis.py
Topsis_SAVITAJ_102016034.egg-info/PKG-INFO
Topsis_SAVITAJ_102016034.egg-info/SOURCES.txt
Topsis_SAVITAJ_102016034.egg-info/dependency_links.txt
Topsis_SAVITAJ_102016034.egg-info/requires.txt
Topsis_SAVITAJ_102016034.egg-info/top_level.txt